ege_classification/__init__.py
ege_classification/__main__.py
ege_classification/huggingface.py
ege_classification/model.py
ege_classification-0.0.4.dist-info/METADATA
ege_classification-0.0.4.dist-info/WHEEL
ege_classification-0.0.4.dist-info/RECORD
