Metadata-Version: 2.3
Name: ege_classification
Version: 0.0.4
Summary: 
License: MIT
Author: Merzlikin-Matvey
Author-email: merzlikinmatvey01@gmail.com
Requires-Python: >=3.12,<4.0
Classifier: License :: OSI Approved :: MIT License
Classifier: Programming Language :: Python :: 3
Classifier: Programming Language :: Python :: 3.12
Classifier: Programming Language :: Python :: 3.13
Requires-Dist: accelerate (>=0.26.0)
Requires-Dist: datasets (>=3.3.2,<3.4.0)
Requires-Dist: flake8 (>=7.1.2,<8.0.0)
Requires-Dist: huggingface-hub (>=0.29.2,<0.30.0)
Requires-Dist: pandas (>=2.2.3,<2.3.0)
Requires-Dist: scikit-learn (>=1.6.1,<1.7.0)
Requires-Dist: torch (>=2.6.0,<2.7.0)
Requires-Dist: transformers (>=4.49.0,<4.50.0)
